LICENSE.txt
README.md
setup.cfg
setup.py
behave_cucumber_formatter/__init__.py
behave_cucumber_formatter.egg-info/PKG-INFO
behave_cucumber_formatter.egg-info/SOURCES.txt
behave_cucumber_formatter.egg-info/dependency_links.txt
behave_cucumber_formatter.egg-info/requires.txt
behave_cucumber_formatter.egg-info/top_level.txt